ovos_listener/__init__.py
ovos_listener/__main__.py
ovos_listener/arecord.py
ovos_listener/data_structures.py
ovos_listener/hotword_factory.py
ovos_listener/listener.py
ovos_listener/mic.py
ovos_listener/service.py
ovos_listener/silence.py
ovos_listener/stt.py
ovos_listener/utils.py
ovos_listener/version.py
ovos_listener/res/snd/acknowledge.mp3
ovos_listener/res/snd/error.mp3
ovos_listener/res/snd/start_listening.wav
ovos_listener-0.0.3.dist-info/LICENSE.md
ovos_listener-0.0.3.dist-info/METADATA
ovos_listener-0.0.3.dist-info/WHEEL
ovos_listener-0.0.3.dist-info/entry_points.txt
ovos_listener-0.0.3.dist-info/top_level.txt
ovos_listener-0.0.3.dist-info/RECORD
