Metadata-Version: 2.1
Name: ovos-listener
Version: 0.0.3
Summary: ovos-core listener daemon client
Home-page: https://github.com/OpenVoiceOS/ovos-listener
Author: UNKNOWN
Author-email: UNKNOWN
License: Apache-2.0
Platform: UNKNOWN
Classifier: Development Status :: 4 - Beta
Classifier: Programming Language :: Python :: 3
Classifier: License :: OSI Approved :: Apache Software License
Requires-Dist: SpeechRecognition>=3.8.1
Requires-Dist: PyAudio~=0.2
Requires-Dist: ovos-vad-plugin-webrtcvad
Requires-Dist: ovos-ww-plugin-pocketsphinx>=0.1.3,~=0.1
Requires-Dist: ovos-ww-plugin-precise-lite>=0.1.2,~=0.1
Requires-Dist: ovos-ww-plugin-vosk
Requires-Dist: ovos-stt-plugin-server>=0.0.2,~=0.0
Requires-Dist: ovos-stt-plugin-vosk~=0.1
Requires-Dist: ovos-utils>=0.0.31,~=0.0
Requires-Dist: ovos-bus-client>=0.0.3a16,~=0.0
Requires-Dist: ovos-plugin-manager>=0.0.23,~=0.0
Requires-Dist: ovos-config>=0.0.8,~=0.0
Requires-Dist: ovos-backend-client>=0.0.6,~=0.0
